bbbmon/__init__.py
bbbmon/bbbmon.py
bbbmon/configuration.py
bbbmon/load.py
bbbmon/meetings.py
bbbmon/printing.py
bbbmon/xmldict.py
bbbmon-0.1.33.dist-info/entry_points.txt
bbbmon-0.1.33.dist-info/LICENSE
bbbmon-0.1.33.dist-info/WHEEL
bbbmon-0.1.33.dist-info/METADATA
bbbmon-0.1.33.dist-info/RECORD
