Metadata-Version: 2.1
Name: bbbmon
Version: 0.1.33
Summary: A small CLI utility to monitor bbb usage
License: GPL-3.0+
Author: David Huss
Author-email: david.huss@hfbk-hamburg.de
Maintainer: David Huss
Maintainer-email: david.huss@hfbk-hamburg.de
Requires-Python: >=3.5,<4.0
Classifier: Development Status :: 4 - Beta
Classifier: Environment :: Console
Classifier: Intended Audience :: System Administrators
Classifier: License :: Free For Educational Use
Classifier: License :: Free for non-commercial use
Classifier: License :: OSI Approved :: GNU General Public License v3 (GPLv3)
Classifier: License :: OSI Approved :: GNU General Public License v3 or later (GPLv3+)
Classifier: Natural Language :: English
Classifier: Programming Language :: Python :: 3
Classifier: Programming Language :: Python :: 3.5
Classifier: Programming Language :: Python :: 3.6
Classifier: Programming Language :: Python :: 3.7
Classifier: Programming Language :: Python :: 3.8
Classifier: Programming Language :: Python :: 3.9
Classifier: Topic :: Communications :: Conferencing
Classifier: Topic :: System :: Monitoring
Requires-Dist: click (>=7.1.2,<8.0.0)
Requires-Dist: click-help-colors (>=0.8,<0.9)
Requires-Dist: requests (>=2.23.0,<3.0.0)
